{
    "﻿原始链接": "https://wenshu.court.gov.cn/website/wenshu/181107ANFZ0BXSK4/index.html?docId=34214e20d0994192ae84d8048c85a0ab",
    "案号": "（2010）金兰刑初字第386号",
    "案件名称": "沈洪甲犯故意伤害罪一审刑事判决书",
    "法院": "浙江省兰溪市人民法院",
    "所属地区": "浙江省兰溪市",
    "案件类型": "刑事案件",
    "案件类型编码": "4",
    "审理程序": "刑事一审",
    "裁判日期": "2010-12-13",
    "公开日期": "2015-12-03",
    "当事人": "沈洪甲",
    "案由": "故意伤害",
    "法律依据": "《中华人民共和国刑法（1997年）》:第二百三十四条第一款；《中华人民共和国刑法（1997年）》:第六十七条第一款；《中华人民共和国刑法（1997年）》:第七十二条第一款；《中华人民共和国刑法（1997年）》:第七十三条第二款；《中华人民共和国刑法（1997年）》:第七十三条第三款",
    "全文": "浙江省兰溪市人民法院刑 事 判 决 书（2010）金兰刑初字第386号公诉机关浙江省兰溪市人民检察院。被告人沈洪甲，农民。因涉嫌故意伤害犯罪于2010年7月20日被兰溪市公安局取保候审。现在家候审。辩护人龚贺胜，浙江溪源律师事务所律师。兰溪市人民检察院以（2010）兰检刑诉字第453号起诉书指控被告人沈洪甲犯故意伤害罪，于2010年12月1日向本院提起公诉。本院依法适用简易程序，公开开庭审理了本案。被告人沈洪甲及其辩护人龚贺胜到庭参加诉讼。现已审理终结。兰溪市人民检察院指控，2010年6月2日下午2时30分许，兰溪市废土公司驾驶员赵洪乙驾驶汽车在兰溪市兰江街道西山路人民医院地块附近停车准备倒废土时与沈洪乙发生争吵，后沈洪乙的儿子沈洪甲赶到现场用拳头击打赵洪乙面部，致赵洪乙牙齿被击打后松动，无法保留而拔除。经法医鉴定，赵洪乙的伤势已经构成轻伤。2010年7月16日，被告人沈洪甲到兰溪市公安局投案自首。在审理过程中，被告人沈洪甲与被害人达成赔偿协议，并支付赔偿金18000元。上述事实，被告人在开庭审理过程中亦无异议，并有被害人赵洪乙的陈述，证人沈洪乙、赵洪甲的证言，兰溪市洪施行政村出具的证明、到案经过、兰溪市公安局法医学人体损伤程度鉴定书、鉴定结论告知书；兰溪市公安局自首证明文书、收条，以及被告人的户籍证明等证据证实，足以认定。本院认为，被告人沈洪甲故意伤害他人身体，致人轻伤，其行为已构成故意伤害罪。公诉机关指控成立，本院予以支持。被告人沈洪甲主动投案并如实供述自己的罪行，系自首，可依法从轻处罚。被告人沈洪甲在案发后主动赔偿被害人损失，归案后认罪态度较好，可酌情从轻处罚。为严肃国法，保护公民的人身权利不受侵犯，依照《中华人民共和国刑法》第二百三十四条第一款、第六十七条第一款、第七十二条第一款、第七十三条第二、三款的规定，判决如下：被告人沈洪甲犯故意伤害罪，判处有期徒刑十个月，缓刑一年二个月（缓刑考验期限，从判决确定之日起计算）。如不服本判决，可于接到判决书的第二日起十日内，通过本院或者直接向浙江省金华市中级人民法院提出上诉。书面上诉的，应提交上诉状正本一份，副本二份。代理审判员　　高春红二〇一〇年十二月十三日代书　记员　　薛黎艳 ："
}