{
    "﻿原始链接": "https://wenshu.court.gov.cn/website/wenshu/181107ANFZ0BXSK4/index.html?docId=b11c08dcac5b4a8db846ab1b00a2ecb1",
    "案号": "（2011）武侯刑初字第17号",
    "案件名称": "柯玉霞盗窃一案一审刑事判决书",
    "法院": "成都市武侯区人民法院",
    "所属地区": "成都市",
    "案件类型": "刑事案件",
    "案件类型编码": "4",
    "审理程序": "刑事一审",
    "裁判日期": "2010-12-27",
    "公开日期": "2019-12-06",
    "当事人": "柯玉霞",
    "案由": "盗窃",
    "法律依据": "《中华人民共和国刑法（1997年）》:第二百六十四条；《中华人民共和国刑法（1997年）》:第二百六十四条第一项；《中华人民共和国刑法（1997年）》:第二百六十四条第二项；《中华人民共和国刑法（1997年）》:第五十二条；《中华人民共和国刑法（1997年）》:第五十三条；《中华人民共和国刑法（1997年）》:第十九条",
    "全文": "  成都市武侯区人民法院 刑 事 判 决 书 （2011）武侯刑初字第17号 公诉机关成都市武侯区人民检察院。 被告人柯玉霞（聋哑人），女，1971年8月30日出生于重庆市万盛区，汉族，小学文化程度，无业，户籍所在地为重庆市万盛区。2006年8月10日因犯盗窃罪被成都市锦江区人民法院判处拘役五个月，2006年9月25日刑满释放；2010年8月16日因吸毒被成都市公安局武侯区分局决定强制戒毒两年，2010年9月20日因本案被逮捕。现羁押于成都市看守所。 指定辩护人余刚，四川志顺律师事务所律师。 手语翻译人丁寿昌，成都市特殊教育学校教师。 成都市武侯区人民检察院以成武检刑诉字（2010）第806号起诉书指控被告人柯玉霞犯盗窃罪，于2010年12月10日向本院提起公诉。本院依法组成合议庭，公开开庭审理了本案。成都市武侯区人民检察院指派代理检察员夏卫出庭支持公诉，被告人柯玉霞及其指定辩护人余刚、手语翻译人丁寿昌到庭参加诉讼。现已审理终结。 成都市武侯区人民检察院指控，2010年8月16日11时许，被告人柯玉霞在本市武侯区华西附二院院内，趁被害人杨建在建卡处排队时，将其挎包拉链拉开，盗走其现金人民币2635元，后被民警现场抓获。 被告人柯玉霞及其辩护人对公诉机关指控的犯罪事实和罪名均无异议；对公诉机关提出对被告人适用6到10个月有期徒刑的量刑建议无异议。 经审理查明，被告人柯玉霞系聋哑人，2010年8月16日11时许，被告人柯玉霞在本市武侯区华西附二院院内，趁被害人杨建在建卡处排队时，将其挎包拉链拉开，盗走其现金人民币2635元，后被民警现场抓获，所盗赃款追回并发还给被害人。 为支持指控，公诉机关向本院移送的指控证据有：接受刑事案件登记表；挡获经过；扣押及发还物品清单；被告人供述；被害人陈述；现场图及现场照片；毒品尿液检测报告；被告人户籍材料及前科材料等。本案事实清楚、证据充分，足以认定。 本院认为，被告人柯玉霞以非法占有为目的，秘密窃取他人财物，数额较大，其行为已构成盗窃罪。被告人柯玉霞系聋哑人，依法可以从轻处罚；被告人当庭认罪，悔罪态度较好，酌情予以从轻处罚；本案中所盗赃款已追回，并发还被害人，可以酌情予以从轻处罚；被告人柯玉霞有犯罪前科，且有吸毒恶习，酌情予以从重处罚。成都市武侯区人民检察院起诉指控被告人柯玉霞犯盗窃罪的罪名成立，予以支持；公诉机关提出的量刑建议，合法适当，予以采纳。被告人柯玉霞的辩护人提出被告人系聋哑人，认罪态度较好，赃款追回，请求从轻处罚的辩护意见，与本院查明的事实及证据相符，予以采纳。为保护公民的财产权利不受侵犯，惩罚犯罪，依照《中华人民共和国刑法》第二百六十四条、第五十二条、第五十三条、第十九条之规定判决如下： 被告人柯玉霞犯盗窃罪，判处有期徒刑七个月，并处罚金人民币1000元。 （刑期从判决执行之日起计算。判决执行以前先行羁押的，羁押一日折抵刑期一日，即从2010年9月20日起至2011年4月19日止。罚金于判决生效之日起十五日内缴纳。） 如不服本判决，可在接到判决书的第二日起十日内，通过本院或直接向四川省成都市中级人民法院提出上诉。书面上诉的，应当提交上诉状正本一份、副本一份。 审　判　长　　高晓强 代理审判员　　张熙杰 人民陪审员　　谢再琼 二０一０年十二月二十七日 书　记　员　　马玲菲 "
}