{
    "﻿原始链接": "https://wenshu.court.gov.cn/website/wenshu/181107ANFZ0BXSK4/index.html?docId=f6872ab21a99427dba353b7abe2e3503",
    "案号": "（2010）杭淳刑初字第347号",
    "案件名称": "刘某盗窃罪一审刑事判决书",
    "法院": "淳安县人民法院",
    "所属地区": "淳安县",
    "案件类型": "刑事案件",
    "案件类型编码": "4",
    "审理程序": "一审",
    "裁判日期": "2010-12-20",
    "公开日期": "2014-08-15",
    "当事人": "刘某",
    "案由": "盗窃",
    "法律依据": "《中华人民共和国刑法（1997年）》：第二百六十四条，第二百六十四条",
    "全文": "浙江省淳安县人民法院刑 事 判 决 书（2010）杭淳刑初字第347号公诉机关浙江省淳安县人民检察院。被告人刘某。2009年12月因吸毒被杭州市公安局萧山分局行政拘留十日，2010年10月10日因本案被淳安县公安局刑事拘留，同年11月8日被依法逮捕。现押于淳安县看守所。浙江省淳安县人民检察院以淳检刑诉（2010）350号起诉书指控被告人刘某犯盗窃罪，于2010年12月15日向本院提起公诉。本院依法适用简易程序，实行独任审判，公开开庭审理了本案。被告人刘某到庭参加诉讼。现已审理终结。公诉机关指控：2010年9月30日凌晨，被告人刘某被被害人邵某某带至千岛湖新玉丽宾馆607房间嫖宿。早上7时许，被告人刘某趁被害人熟睡之际，窃取被害人衣服口袋和裤子口袋里的现金人民币共计11500元，随后窜逃至杭州萧山。案发后，被告人刘某向本院退出赃款11500元。另查明，公安机关经侦查后将被告人刘某抓获归案。上述事实，被告人刘某在开庭审理过程中亦无异议，并有被害人邵某某的陈述，证人杨*等的证言，视听资料新玉丽宾馆607房间门口走廊监控录像光盘一片、监控视频截图照片、POS机取款凭证、浙江省农村合作金融机构分户明细对账单、扣押物品文件清单、前科材料、抓获经过、户籍证明、案款收据等证据证实，足以认定。本院认为，被告人刘某以非法占有为目的，采用秘密手段窃取他人财物，数额较大，其行为已构成盗窃罪，公诉机关指控被告人刘某犯盗窃罪的事实与罪名成立。被告人刘某有劣迹前科，酌情从重处罚，被告人自愿认罪，并退出全部赃款，可以酌情从轻处罚。根据被告人刘某犯罪的事实、性质、情节和对社会的危害程度，依照《中华人民共和国刑法》第二百六十四条之规定，判决如下：被告人刘某犯盗窃罪，判处有期徒刑一年六个月，并处罚金人民币3000元。（刑期从判决执行之日起计算，判决执行前先行羁押的，羁押一日折抵刑期一日，即自2010年10月10日起至2012年4月9日止。罚金于判决生效后十日内缴纳。）如不服本判决，可于接到判决书的第二日起十日内，通过本院或直接向浙江省杭州市中级人民法院提出上诉。书面上诉的，应交上诉状正本一份，副本二份。审判员　　席维花二〇一〇年十二月二十日书记员　　郑苏程"
}