{
    "﻿原始链接": "https://wenshu.court.gov.cn/website/wenshu/181107ANFZ0BXSK4/index.html?docId=32fc7e8067714467b59c4bb5859d86e5",
    "案号": "（2009）临执字第152号",
    "案件名称": "建设工程施工合同纠纷执行裁定书",
    "法院": "淄博市临淄区人民法院",
    "所属地区": "淄博市",
    "案件类型": "执行案件",
    "案件类型编码": "2",
    "审理程序": "",
    "裁判日期": "2010-12-20",
    "公开日期": "2016-04-19",
    "当事人": "",
    "案由": "",
    "法律依据": "《中华人民共和国民事诉讼法（2007年）》：第二百五十七条",
    "全文": "山东省淄博市临淄区人民法院执 行 裁 定 书（2009）临执字第152号赵*申请执行毕*建设工程承包合同纠纷一案，本院作出的（2008）临民初字第3011号民事判决书已经发生法律效力，权利人赵*怀于2008年12月30日向本院申请执行。本院于同日立案执行。本案在执行过程中，执行标的33068元未能执行。现查明被执行人毕*敏无财产可供执行，申请执行人赵建怀也提供不出被执行人毕*敏有可供执行的财产证据或财产线索，经合议庭合议认为，该案符合终结本次执行程序的条件，依照《中华人民共和国民事诉讼法》第二百五十七条第（六）项之规定，裁定如下：淄博市临淄区人民法院（2009）临执字第152号执行案件本次执行程序终结执行。如发现被执行人毕玉敏有财产可供执行，申请执行人赵*怀可以向有管辖权的人民法院申请执行剩余债权。本裁定书送达后立即生效。审判长　　李爱民审判员　　王建勋审判员　　张　晔二〇一〇年十二月二十日书记员　　于雪莲 "
}