{
    "﻿原始链接": "https://wenshu.court.gov.cn/website/wenshu/181107ANFZ0BXSK4/index.html?docId=b1142149cee241df8556c6939cf4c9f7",
    "案号": "（2010）碑执字第796号",
    "案件名称": "贾某安与邝某宁、黄某珍债务纠纷一案执行裁定书",
    "法院": "西安市碑林区人民法院",
    "所属地区": "西安市",
    "案件类型": "执行案件",
    "案件类型编码": "2",
    "审理程序": "",
    "裁判日期": "2010-12-12",
    "公开日期": "2014-12-18",
    "当事人": "贾某安,邝某宁,黄某珍",
    "案由": "",
    "法律依据": "《中华人民共和国民事诉讼法（2007年）》：第二百三十三条",
    "全文": "西安市碑林区人民法院执 行 裁 定 书（2010）碑执字第796号申请执行人贾某安，女，1953年9月1日出生，汉族，西安电力机械制造公司第2中学退休教师。被执行人邝某宁，男，1955年1月13日出生，汉族。被执行人黄某珍，女，1962年2月2日出生，汉族，西安市粮食局雁塔分局职工。本院在执行贾某安与邝某宁、黄某珍债务纠纷一案中，被执行人已按本院（2009）碑民二初字第729号民事判决书履行了全部义务。依照《中华人民共和国民事诉讼法》第二百三十三条第（六）项的规定，裁定如下：终结本院（2009）碑民二初字第729号民事判决书的执行。本裁定送达后立即生效。（此页无正文）审　判　长　　梅宏枝审　判　员　　曹　坤代理审判员　　夏怀山二〇一〇年十二月十二日书　记　员　　王　勇 "
}